LICENSE
MANIFEST.in
README.rst
setup.cfg
setup.py
versioneer.py
tests/__init__.py
tests/test_general.py
tpDcc/__init__.py
tpDcc/__logging__.ini
tpDcc/__version__.py
tpDcc/_version.py
tpDcc/loader.py
tpDcc/abstract/__init__.py
tpDcc/abstract/callback.py
tpDcc/abstract/dialog.py
tpDcc/abstract/menu.py
tpDcc/abstract/progressbar.py
tpDcc/abstract/scene.py
tpDcc/abstract/sceneobject.py
tpDcc/abstract/scenewrapper.py
tpDcc/abstract/shelf.py
tpDcc/abstract/window.py
tpDcc/core/__init__.py
tpDcc/core/client.py
tpDcc/core/command.py
tpDcc/core/config.py
tpDcc/core/consts.py
tpDcc/core/dcc.py
tpDcc/core/exceptions.py
tpDcc/core/library.py
tpDcc/core/node.py
tpDcc/core/options.py
tpDcc/core/plugin.py
tpDcc/core/project.py
tpDcc/core/reroute.py
tpDcc/core/scene.py
tpDcc/core/server.py
tpDcc/core/tool.py
tpDcc/core/utils.py
tpDcc/dcc/__init__.py
tpDcc/dcc/callback.py
tpDcc/dcc/dialog.py
tpDcc/dcc/progressbar.py
tpDcc/dcc/window.py
tpDcc/dccs/__init__.py
tpDcc/libs/__init__.py
tpDcc/managers/__init__.py
tpDcc/managers/callbacks.py
tpDcc/managers/configs.py
tpDcc/managers/libs.py
tpDcc/managers/logs.py
tpDcc/managers/menus.py
tpDcc/managers/plugins.py
tpDcc/managers/resources.py
tpDcc/managers/tools.py
tpDcc/tools/__init__.py
tpDcc/toolsets/__init__.py
tpDcc/toolsets/general.toolset
tpDcc_core.egg-info/PKG-INFO
tpDcc_core.egg-info/SOURCES.txt
tpDcc_core.egg-info/dependency_links.txt
tpDcc_core.egg-info/not-zip-safe
tpDcc_core.egg-info/requires.txt
tpDcc_core.egg-info/top_level.txt