Metadata-Version: 2.1
Name: tpDcc-core
Version: 0.0.30
Summary: Core module for tpDcc. Includes core modules to use DCC Python APIs in a DCC agnostic way
Home-page: https://github.com/tpDcc/tpDcc-core
Author: Tomas Poveda
Author-email: tpovedatd@gmail.com
License: MIT
Platform: UNKNOWN
Provides-Extra: dev
Provides-Extra: test
